mogutda/__init__.py
mogutda/abssimcomplex.py
mogutda/alphacomplex.py
mogutda/utils.py
mogutda/vrcomplex.py
mogutda-0.4.5.dist-info/licenses/LICENSE
mogutda-0.4.5.dist-info/METADATA
mogutda-0.4.5.dist-info/WHEEL
mogutda-0.4.5.dist-info/top_level.txt
mogutda-0.4.5.dist-info/RECORD
