Metadata-Version: 2.4
Name: mogutda
Version: 0.4.5
Summary: Topological Data Analysis in Python
Author-email: Kwan Yuet Stephen Ho <stephenhky@yahoo.com.hk>
License: MIT
Project-URL: Documentation, https://mogutda.readthedocs.io
Project-URL: Repository, https://github.com/stephenhky/MoguTDA
Project-URL: Issues, https://github.com/stephenhky/MoguTDA/issues
Keywords: mogutda,numerical methods,topology,data,algebraic topology
Classifier: Topic :: Scientific/Engineering :: Mathematics
Classifier: Topic :: Scientific/Engineering :: Physics
Classifier: Programming Language :: Python :: 3.8
Classifier: Programming Language :: Python :: 3.9
Classifier: Programming Language :: Python :: 3.10
Classifier: Programming Language :: Python :: 3.11
Classifier: Programming Language :: Python :: 3.12
Classifier: Programming Language :: Python :: 3.13
Classifier: License :: OSI Approved :: MIT License
Classifier: Intended Audience :: Developers
Classifier: Intended Audience :: Education
Classifier: Intended Audience :: Information Technology
Classifier: Intended Audience :: Science/Research
Requires-Python: >=3.8
License-File: LICENSE
Requires-Dist: numpy>=1.16.0
Requires-Dist: scipy>=1.10.0
Requires-Dist: networkx>=2.0
Requires-Dist: matplotlib>=3.3.0
Provides-Extra: test
Requires-Dist: unittest; extra == "test"
Requires-Dist: pytest; extra == "test"
Dynamic: license-file
